{
  "android": {
    "qd_code": "QDAND",
    "description": "Qodana for Android (https://jb.gg/qodana-android)",
    "from": "jvm"
  },
  "android-community": {
    "qd_code": "QDANDC",
    "description": "Qodana Community for Android (https://jb.gg/qodana-android)",
    "from": "jvm-community"
  },
  "cpp": {
    "qd_code": "QDCPP",
    "description": "Qodana for C++ (https://jb.gg/qodana-cpp)"
  },
  "cpp-community": {
    "qd_code": "QDCL",
    "description": "Qodana for C/C++ (https://jb.gg/qodana-clang)",
    "is_third_party": true
  },
  "dotnet": {
    "qd_code": "QDNET",
    "description": "Qodana for .NET (https://jb.gg/qodana-dotnet)"
  },
  "dotnet-community": {
    "qd_code": "QDNETC",
    "description": "Qodana Community for .NET (https://jb.gg/qodana-dotnet)",
    "is_third_party": true
  },
  "go": {
    "qd_code": "QDGO",
    "description": "Qodana for Go (https://jb.gg/qodana-go)"
  },
  "js": {
    "qd_code": "QDJS",
    "description": "Qodana for JS (https://jb.gg/qodana-js)"
  },
  "jvm": {
    "qd_code": "QDJVM",
    "description": "Qodana for JVM (https://jb.gg/qodana-jvm)"
  },
  "jvm-community": {
    "qd_code": "QDJVMC",
    "description": "Qodana Community for JVM (https://jb.gg/qodana-jvm)"
  },
  "php": {
    "qd_code": "QDPHP",
    "description": "Qodana for PHP (https://jb.gg/qodana-php)"
  },
  "python": {
    "qd_code": "QDPY",
    "description": "Qodana for Python (https://jb.gg/qodana-python)"
  },
  "python-community": {
    "qd_code": "QDPYC",
    "description": "Qodana Community for Python (https://jb.gg/qodana-python)"
  },
  "ruby": {
    "qd_code": "QDRUBY",
    "description": "Qodana for Ruby (https://jb.gg/qodana-ruby)"
  }
}
